community_codeswarm.py
setup.py
Community_Codeswarm.egg-info/PKG-INFO
Community_Codeswarm.egg-info/SOURCES.txt
Community_Codeswarm.egg-info/dependency_links.txt
Community_Codeswarm.egg-info/top_level.txt