Metadata-Version: 1.1
Name: Community-Codeswarm
Version: 0.2.1
Summary: ['Create combined code_swarms from several different source repositories. ']
Home-page: http://rakjar.de/shared_codeswarm
Author: Arne Babenhauserheide
Author-email: arne_bab@web.de
License: GNU GPL-3 or later
Keywords: codeswarm,Mercurial
Platform: any
Classifier: License :: OSI Approved :: GNU General Public License (GPL)
Classifier: Programming Language :: Python
Classifier: Operating System :: OS Independent
Classifier: Intended Audience :: Developers
Classifier: Intended Audience :: End Users/Desktop
Classifier: Environment :: Console
Classifier: Development Status :: 3 - Alpha
Requires: yaml
Requires: mercurial
